[{"timestamp":"2024-11-01T01:18:04.064Z","count":0,"uniques":0},{"timestamp":"2024-12-01T01:18:04.064Z","count":2,"uniques":1},{"timestamp":"2025-01-01T01:04:35.187Z","count":14,"uniques":6},{"timestamp":"2025-02-01T06:18:07.341Z","count":8,"uniques":3},{"timestamp":"2025-03-01T18:19:26.253Z","count":3,"uniques":2},{"timestamp":"2025-04-01T01:11:24.905Z","count":1,"uniques":1},{"timestamp":"2025-05-01T18:24:26.915Z","count":0,"uniques":0},{"timestamp":"2025-06-01T18:24:26.915Z","count":0,"uniques":0},{"timestamp":"2025-07-01T01:23:44.240Z","count":96,"uniques":2},{"timestamp":"2025-08-01T06:27:51.854Z","count":3,"uniques":3},{"timestamp":"2025-09-01T06:23:13.458Z","count":3,"uniques":2},{"timestamp":"2025-10-01T01:12:52.909Z","count":1,"uniques":1},{"timestamp":"2025-11-01T01:19:59.588Z","count":0,"uniques":0}]
